{
  "id": 213,
  "url": "https://www.psychologytoday.com/sg/tests/personality/extroversion-introversion-test",
  "original_title": "Introversion / Extroversion Test",
  "processed_title": "Introversion / Extroversion Test",
  "content": "If you're highly outgoing, talkative, and assertive, you may be an extrovert. If you draw your energy from time alone or in smaller groups, you may be an introvert. If you’re like most people, though, you’re probably somewhere in between. Find out where you land on the spectrum of extroversion, one of the Big Five personality traits. Using the key below, answer the questions based on how strongly you agree or disagree with the statement. This test is for anyone curious about their personality traits, or concerned that they may be too introverted or too extroverted. This test is not intended to be diagnostic. If you think this aspect of your personality is holding you back personally or professionally, you can speak to a mental health professional about ways to shift your behavior. You can find one near you in the Psychology Today Therapy Directory.",
  "summary": "Tes Introverensi/Extroverensi membantu seseorang memahami apakah mereka cenderung lebih aktif, berbicara, dan percaya diri (extrovert), atau lebih tenang, membutuhkan waktu sendiri, dan menikmati keheningan (introvert). Banyak orang berada di tengah-tengah antara dua ekstrem tersebut. Tes ini merupakan bagian dari lima karakteristik kepribadian besar, yaitu kepribadian yang diukur secara objektif. Seseorang dapat menilai diri dengan menjawab pertanyaan berdasarkan sejauh mana mereka setuju atau tidak setuju dengan pernyataan tertentu. Tes ini dirancang untuk memberikan wawasan tentang sifat kepribadian seseorang, terutama dalam hal kecenderungan sosial dan energi. Namun, perlu dipahami bahwa tes ini bukan diagnosis medis atau psikologis. Jika seseorang merasa bahwa sifat ini memengaruhi kehidupan pribadi atau profesional, disarankan untuk berkonsultasi dengan profesional kesehatan mental, seperti psikolog atau psikoterapis. Dalam konteks psikologi Islam, konsep tazkiyatun nufus (perbaikan jiwa) juga relevan, karena menekankan pentingnya keseimbangan antara kegiatan sosial dan keheningan, serta keberadaan diri dalam kehidupan. Keseimbangan ini bisa membantu seseorang mengelola diri secara sehat, memenuhi kebutuhan spiritual, dan mempertahankan kesehatan mental. Dengan memahami sifat kepribadian, seseorang dapat memilih cara berinteraksi, mengelola energi, dan membangun hubungan yang sehat. Tes ini bisa menjadi awal untuk refleksi diri, namun tetap perlu bantuan profesional jika diperlukan.",
  "content_length": 864,
  "chunks_total": 1,
  "chunks_relevant": 1,
  "vectors": [
    {
      "chunk_index": 1,
      "chunk_text": "If you're highly outgoing, talkative, and assertive, you may be an extrovert. If you draw your energy from time alone or in smaller groups, you may be an introvert. If you’re like most people, though, you’re probably somewhere in between. Find out where you land on the spectrum of extroversion, one of the Big Five personality traits. Using the key below, answer the questions based on how strongly you agree or disagree with the statement. This test is for anyone curious about their personality traits, or concerned that they may be too introverted or too extroverted. This test is not intended to be diagnostic. If you think this aspect of your personality is holding you back personally or professionally, you can speak to a mental health professional about ways to shift your behavior. You can find one near you in the Psychology Today Therapy Directory.",
      "embedding": [
        -0.011866962537169456,
        0.06349722295999527,
        -0.02791549079120159,
        -0.007864095270633698,
        -0.03255109116435051,
        -0.022878920659422874,
        0.0680651068687439,
        0.038723669946193695,
        0.0009666017722338438,
        0.033565983176231384,
        0.15352968871593475,
        -0.05494692176580429,
        0.0007261707214638591,
        -0.049013759940862656,
        -0.008899618871510029,
        0.009297599084675312,
        0.029274320229887962,
        0.020648019388318062,
        -0.03619036823511124,
        0.0020974918734282255,
        -0.026636892929673195,
        0.015454462729394436,
        -0.008017923682928085,
        0.0012105333153158426,
        -0.0813787505030632,
        -0.006728607229888439,
        -0.017077069729566574,
        -0.004558243323117495,
        0.09392771869897842,
        -0.024689234793186188,
        0.00005313197470968589,
        0.04325976222753525,
        0.09641848504543304,
        -0.0018145069479942322,
        -0.020730014890432358,
        0.07563517987728119,
        0.002241509035229683,
        0.07283934950828552,
        0.01063039992004633,
        0.049183204770088196,
        -0.04789571091532707,
        -0.03513598069548607,
        -0.028061019256711006,
        -0.12693926692008972,
        0.04228672757744789,
        -0.07077287137508392,
        -0.0531618706882,
        0.006878470536321402,
        0.07236496359109879,
        -0.0458306223154068,
        -0.10826610028743744,
        0.002042836043983698,
        -0.03649447485804558,
        -0.04490538686513901,
        0.05558708310127258,
        -0.14503733813762665,
        -0.026321185752749443,
        0.045387037098407745,
        0.014269440434873104,
        0.011319475248456001,
        0.07285965979099274,
        0.08443965017795563,
        -0.009054681286215782,
        -0.001732312492094934,
        0.05855073407292366,
        0.022959375753998756,
        -0.04102862626314163,
        0.002713366411626339,
        -0.014689581468701363,
        0.008020739071071148,
        0.04168136417865753,
        -0.06948840618133545,
        -0.033605653792619705,
        0.03590119630098343,
        -0.15525425970554352,
        0.013135425746440887,
        -0.007624603807926178,
        0.014874753542244434,
        -0.04354126751422882,
        -0.0004236460954416543,
        0.06909871846437454,
        -0.025910979136824608,
        -0.01803525909781456,
        -0.05853841081261635,
        -0.09691262245178223,
        -0.009335506707429886,
        -0.02812741883099079,
        0.017952119931578636,
        -0.01788162812590599,
        0.009174344129860401,
        0.0016050159465521574,
        -0.003663873765617609,
        -0.0922524705529213,
        -0.05646687000989914,
        -0.003508226480334997,
        0.00012677123595494777,
        -0.12563616037368774,
        -0.07567238062620163,
        0.011768350377678871,
        0.008495187386870384,
        -0.006312747951596975,
        0.005885877180844545,
        -0.01912355050444603,
        0.0006342977867461741,
        -0.13498377799987793,
        -0.09127364307641983,
        0.04040699824690819,
        -0.07469417154788971,
        0.0976412296295166,
        0.043075818568468094,
        -0.0757034569978714,
        -0.07740092277526855,
        -0.08217498660087585,
        -0.06417807191610336,
        0.029191292822360992,
        0.0443243645131588,
        -0.042559076100587845,
        0.01346465852111578,
        0.0402316153049469,
        0.03284158930182457,
        0.0011996388202533126,
        0.015408705919981003,
        0.0654156282544136,
        0.019722728058695793,
        0.021504806354641914,
        -0.04657595232129097,
        -0.0011497692903503776,
        2.163861902873969e-32,
        0.02715206705033779,
        -0.057523179799318314,
        0.053913310170173645,
        0.03577172011137009,
        -0.023928334936499596,
        -0.034587908536195755,
        -0.03652352839708328,
        -0.1323396861553192,
        0.017541278153657913,
        -0.011414009146392345,
        0.039819587022066116,
        -0.007966766133904457,
        -0.008167283609509468,
        -0.035583268851041794,
        0.04268178716301918,
        -0.01740279793739319,
        -0.00253790314309299,
        -0.05513272061944008,
        -0.08110247552394867,
        -0.001333017135038972,
        0.00566583126783371,
        0.029303988441824913,
        -0.0017911699833348393,
        -0.11405234783887863,
        0.006815549451857805,
        -0.015329881571233273,
        -0.04301973059773445,
        0.005580107681453228,
        0.019738314673304558,
        0.013385572470724583,
        0.08587511628866196,
        0.019938986748456955,
        -0.1090664491057396,
        -0.027923982590436935,
        -0.0709092915058136,
        -0.01766972616314888,
        0.0442952997982502,
        -0.05012432113289833,
        0.023165825754404068,
        -0.09726329147815704,
        -0.07846559584140778,
        -0.019837435334920883,
        0.006439689081162214,
        0.03976647928357124,
        0.0308579932898283,
        0.08103007078170776,
        0.046390239149332047,
        -0.01172433141618967,
        0.0736255869269371,
        0.047780390828847885,
        -0.04077015072107315,
        0.018738286569714546,
        0.0070602684281766415,
        -0.06389627605676651,
        0.022692378610372543,
        0.01582203432917595,
        -0.011554580181837082,
        0.04744627699255943,
        -0.005634568631649017,
        0.0006574485450983047,
        -0.05328424274921417,
        -0.005834159906953573,
        -0.04521123319864273,
        -0.03172459825873375,
        0.0002698867174331099,
        -0.028725625947117805,
        -0.04420836642384529,
        -0.0014807571424171329,
        0.06787899881601334,
        -0.006171457469463348,
        -0.0692523941397667,
        -0.043724894523620605,
        -0.020228533074259758,
        0.049027882516384125,
        0.0015461897710338235,
        -0.02427257038652897,
        0.015058108605444431,
        0.04898017644882202,
        -0.04817036911845207,
        0.07895396649837494,
        -0.043763019144535065,
        0.06440314650535583,
        -0.028119519352912903,
        -0.02507920190691948,
        0.03388603404164314,
        0.08530660718679428,
        -0.02488642930984497,
        -0.03250088170170784,
        0.09440992772579193,
        0.06353319436311722,
        0.01248474232852459,
        0.054605916142463684,
        0.005555716808885336,
        0.0542350672185421,
        -0.02123042196035385,
        -2.1282838031048062e-32,
        0.05600942298769951,
        0.04684972018003464,
        -0.0716104805469513,
        -0.01510679628700018,
        0.04839463159441948,
        0.040323734283447266,
        -0.05005921050906181,
        0.058845773339271545,
        -0.024258004501461983,
        -0.03353236988186836,
        -0.04958465322852135,
        -0.0126883490011096,
        0.15070702135562897,
        0.030645575374364853,
        -0.08770648390054703,
        0.02140379138290882,
        0.0614483617246151,
        0.12630467116832733,
        -0.04091701656579971,
        -0.09568990021944046,
        -0.021120144054293633,
        0.061354123055934906,
        -0.028560955077409744,
        -0.04095359146595001,
        -0.017780499532818794,
        0.051591794937849045,
        0.0156509168446064,
        0.02625581994652748,
        -0.09318751841783524,
        -0.0688987746834755,
        0.05611724406480789,
        0.018050340935587883,
        -0.07708287984132767,
        0.06379628926515579,
        -0.016028491780161858,
        -0.057557061314582825,
        -0.03747877851128578,
        -0.05771227926015854,
        -0.007126087322831154,
        0.024106964468955994,
        -0.016636479645967484,
        0.067446768283844,
        0.05575556680560112,
        -0.07398846745491028,
        -0.07163872569799423,
        -0.05316772684454918,
        0.03899199143052101,
        -0.030038075521588326,
        -0.0322004072368145,
        -0.0673668384552002,
        0.058081090450286865,
        0.037395160645246506,
        0.010561702772974968,
        -0.014884757809340954,
        0.0718376487493515,
        0.01393658947199583,
        0.05218604579567909,
        0.02221575379371643,
        -0.037874866276979446,
        0.021943828091025352,
        -0.0018392084166407585,
        0.004925926681607962,
        0.044410742819309235,
        0.012017170898616314,
        0.03971215710043907,
        0.0323566235601902,
        0.0589781254529953,
        0.06795141845941544,
        0.05694554001092911,
        -0.05451497435569763,
        0.004726864863187075,
        -0.12974214553833008,
        -0.08111358433961868,
        0.03837653249502182,
        -0.024001045152544975,
        -0.01167440228164196,
        -0.06137409433722496,
        -0.059448666870594025,
        0.02365132048726082,
        -0.047876253724098206,
        -0.013762678019702435,
        -0.039669957011938095,
        -0.053390368819236755,
        -0.02185956947505474,
        -0.013795217499136925,
        0.012125684879720211,
        -0.04434138163924217,
        -0.013976262882351875,
        0.0708499625325203,
        0.036935366690158844,
        -0.003863658057525754,
        0.03158656880259514,
        -0.015584681183099747,
        0.059086963534355164,
        0.03619435057044029,
        -6.936219421049827e-8,
        -0.02805633284151554,
        -0.08949675410985947,
        0.044948674738407135,
        0.03091471455991268,
        0.0061421021819114685,
        -0.00828256830573082,
        0.09295851737260818,
        -0.053784266114234924,
        -0.06734468042850494,
        -0.005882003344595432,
        -0.02322625368833542,
        -0.009532509371638298,
        -0.016937656328082085,
        0.033293675631284714,
        0.005626768339425325,
        -0.04324871301651001,
        0.12801989912986755,
        0.06199880689382553,
        -0.006961331702768803,
        -0.02772320806980133,
        0.023492075502872467,
        -0.06327550113201141,
        -0.017374930903315544,
        -0.05898921564221382,
        -0.07722930610179901,
        0.03831607475876808,
        0.01718767173588276,
        -0.013667035847902298,
        0.019526943564414978,
        0.038983095437288284,
        -0.052136365324258804,
        0.08809859305620193,
        -0.030826985836029053,
        -0.07354791462421417,
        -0.06914705038070679,
        0.07495437562465668,
        0.0266586747020483,
        0.015147634781897068,
        -0.07354436069726944,
        0.072395458817482,
        0.03431779146194458,
        -0.013174518011510372,
        0.08931329101324081,
        0.0038734714034944773,
        -0.09303044527769089,
        0.0002698900061659515,
        0.036595433950424194,
        0.07515576481819153,
        0.006456306669861078,
        -0.07962898910045624,
        -0.02899622917175293,
        -0.008949700742959976,
        0.043473485857248306,
        0.029985014349222183,
        -0.03623019903898239,
        0.0037090869154781103,
        -0.029451150447130203,
        0.14627814292907715,
        -0.003618858754634857,
        0.036735184490680695,
        0.0913444310426712,
        0.039410293102264404,
        0.012176936492323875,
        -0.0005846217391081154
      ]
    }
  ],
  "timestamp": "2026-01-02T08:33:45+07:00"
}